mcp_memory/__init__.py
mcp_memory/server.py
mcp_memory-0.1.0.dev2.dist-info/METADATA
mcp_memory-0.1.0.dev2.dist-info/WHEEL
mcp_memory-0.1.0.dev2.dist-info/entry_points.txt
mcp_memory-0.1.0.dev2.dist-info/RECORD
