Metadata-Version: 2.3
Name: mcp-memory
Version: 0.1.0.dev2
Summary: Memory Implementation in MCP and python
Project-URL: Repository, https://github.com/memodb-io/mcp-memory
Project-URL: Issues, https://github.com/memodb-io/mcp-memory/issues
Author-email: Gus <jianbaiye@outlook.com>
Requires-Python: >=3.11
Requires-Dist: mcp>=1.0.0
